valve_gfx_ci/gfxinfo/__init__.py
valve_gfx_ci/gfxinfo/__main__.py
valve_gfx_ci/gfxinfo/amdgpu.py
valve_gfx_ci/gfxinfo/devicetree.py
valve_gfx_ci/gfxinfo/gfxinfo_vulkan.py
valve_gfx_ci/gfxinfo/gpudb.py
valve_gfx_ci/gfxinfo/intel.py
valve_gfx_ci/gfxinfo/nvidia.py
valve_gfx_ci/gfxinfo/pcidevice.py
valve_gfx_ci/gfxinfo/radeon.py
valve_gfx_ci/gfxinfo/test_gfxinfo.py
valve_gfx_ci/gfxinfo/virt.py
valve_gfx_ci/gfxinfo/dbs/DeviceInfo.cpp
valve_gfx_ci/gfxinfo/dbs/drm_pciids.h
valve_gfx_ci/gfxinfo/dbs/i915_pciids.h
valve_gfx_ci/gfxinfo/dbs/nvidia-supportedchips.html
valve_gfx_ci/gfxinfo/dbs/xe_pciids.h
valve_gfx_ci.gfxinfo-0.1.4.dist-info/LICENSE
valve_gfx_ci.gfxinfo-0.1.4.dist-info/METADATA
valve_gfx_ci.gfxinfo-0.1.4.dist-info/WHEEL
valve_gfx_ci.gfxinfo-0.1.4.dist-info/entry_points.txt
valve_gfx_ci.gfxinfo-0.1.4.dist-info/top_level.txt
valve_gfx_ci.gfxinfo-0.1.4.dist-info/RECORD
