Metadata-Version: 2.1
Name: valve_gfx_ci.gfxinfo
Version: 0.1.4
Summary: Generate a list of tags that describe the environment running a GFX workload
Home-page: https://gitlab.freedesktop.org/gfx-ci/ci-tron/-/tree/master/gfxinfo
Author: Martin Roukala
Author-email: martin.roukala@mupuf.org
Project-URL: Bug Tracker, https://gitlab.freedesktop.org/gfx-ci/ci-tron/issues
Classifier: Programming Language :: Python :: 3
Classifier: License :: OSI Approved :: MIT License
Classifier: Operating System :: OS Independent
Requires-Python: >=3.6
License-File: LICENSE
Requires-Dist: requests<3,>=2
Requires-Dist: backports.cached-property; python_version < "3.8"
Provides-Extra: vulkan
Requires-Dist: chturne-vulkan; extra == "vulkan"
